{
  "specificCharacterSet": "ISO_IR 192",
  "imageType": "ORIGINAL\\PRIMARY\\M\\NORM\\DIS2D\\FM3_3\\FIL",
  "instanceCreationDate": "20240130",
  "instanceCreationTime": "134119.998000",
  "sopClassUID": "",
  "sopInstanceUID": "1.3.12.2.1107.5.2.30.59178.202401301341183831060475",
  "studyDate": "20240130",
  "seriesDate": "20240130",
  "acquisitionDate": "20240130",
  "contentDate": "20240130",
  "studyTime": "132931.513000",
  "seriesTime": "134117.968000",
  "acquisitionTime": "133844.485000",
  "contentTime": "134119.998000",
  "accessionNumber": "FWEAB19000010101",
  "modality": "MR",
  "manufacturer": "SIEMENS",
  "institutionName": "Wizjamed",
  "referringPhysicianName": "Dragon^Maciej^^8732055",
  "stationName": "dubai study",
  "studyDescription": "MR kregoslupa LS z kontrastem",
  "performingPhysicianName": "",
  "institutionalDepartmentName": "Department",
  "operatorsName": "Aleksandra Nowodworska",
  "manufacturerModelName": "Avanto",
  "patientName": "dubai study",
  "patientId": "FWEAP19000010232",
  "patientBirthDate": "19730310",
  "patientSex": "M",
  "patientAge": "050Y",
  "patientSize": "1.88",
  "patientWeight": "88",
  "bodyPartExamined": "LSPINE",
  "deviceSerialNumber": "59178",
  "softwareVersions": "syngo MR D13",
  "protocolName": "t2_tse_tra",
  "patientPosition": "HFS",
  "studyId": "16275",
  "seriesNumber": "6",
  "instanceNumber": "35",
  "imagePositionPatient": "-121.01468228339\\-66.370898427509\\-114.72241106516",
  "imageOrientationPatient": "",
  "sliceLocation": "-100.61300962492",
  "samplesPerPixel": "",
  "photometricInterpretation": "MONOCHROME2",
  "rows": "",
  "columns": "",
  "pixelSpacing": "0.44921875\\0.44921875",
  "bitsAllocated": "",
  "bitsStored": "",
  "highBit": "",
  "pixelRepresentation": "",
  "windowCenter": "478",
  "windowWidth": "986"
}